pyframeuz/__init__.py
pyframeuz/app.py
pyframeuz/middleware.py
pyframeuz/orm.py
pyframeuz/response.py
pyframeuz-0.2.0.dist-info/METADATA
pyframeuz-0.2.0.dist-info/WHEEL
pyframeuz-0.2.0.dist-info/top_level.txt
pyframeuz-0.2.0.dist-info/RECORD
